syndatagenyolo/__init__.py
syndatagenyolo/cli/__init__.py
syndatagenyolo/cli/data_generation_cli.py
syndatagenyolo/cli/dataset_mixer_cli.py
syndatagenyolo/cli/extract_cli.py
syndatagenyolo/cli/extract_labelme_from_folder_cli.py
syndatagenyolo/cli/extract_to_yolo_cli.py
syndatagenyolo/cli/main.py
syndatagenyolo/cli/show_images_with_bboxes_cli.py
syndatagenyolo/data_generation.py
syndatagenyolo/dataset_mixer.py
syndatagenyolo/extract.py
syndatagenyolo/extract_labelme_from_folder.py
syndatagenyolo/extract_to_yolo.py
syndatagenyolo/show_images_with_bboxes.py
syndatagenyolo/syndatagenyolo.egg-info/PKG-INFO
syndatagenyolo/syndatagenyolo.egg-info/SOURCES.txt
syndatagenyolo/syndatagenyolo.egg-info/dependency_links.txt
syndatagenyolo/syndatagenyolo.egg-info/entry_points.txt
syndatagenyolo/syndatagenyolo.egg-info/requires.txt
syndatagenyolo/syndatagenyolo.egg-info/top_level.txt
syndatagenyolo/templates/default_augmentation.yml
syndatagenyolo/utils/__init__.py
syndatagenyolo/utils/blending.py
syndatagenyolo/utils/classes_yaml.py
syndatagenyolo/utils/data_gen.py
syndatagenyolo/utils/modes.py
syndatagenyolo-0.2.0.dist-info/licenses/LICENSE
syndatagenyolo-0.2.0.dist-info/WHEEL
syndatagenyolo-0.2.0.dist-info/entry_points.txt
syndatagenyolo-0.2.0.dist-info/METADATA
syndatagenyolo-0.2.0.dist-info/RECORD
