Metadata-Version: 2.4
Name: syndatagenyolo
Version: 0.2.0
Summary: A package for generating synthetic data, using labelme and generating synthetic images.
Author: Sebastian Jörz
Author-email: Sebastian Jörz <seppel8426@gmail.com>
License-File: LICENSE
Requires-Dist: albumentations>=2.0.8
Requires-Dist: joblib>=1.5.1
Requires-Dist: kaggle>=1.7.4.5
Requires-Dist: labelme>=5.8.3
Requires-Dist: scikit-image>=0.25.2
Requires-Dist: shapely>=2.1.1
Requires-Dist: torch>=2.8.0
Requires-Dist: torchvision>=0.23.0
Requires-Dist: ultralytics>=8.3.175
